{
  "_source": "Extracted directly from PPTX_Reference.pptx, Assessment PDF, Presentation PDF, and Summary PDF",
  "colors": {
    "primaryDark": "#4A6631",
    "primary": "#4B6A33",
    "primaryLight": "#8A9A5B",
    "secondaryDark": "#AE7940",
    "secondary": "#B37C4C",
    "secondaryAlt": "#C06C4D",
    "background": "#E6E5DE",
    "slideBackground": "#FFFFFF",
    "text": "#000000",
    "textMuted": "#5E6A71",
    "border": "#D1CFC6",
    "decorCircle1": "#8A9A5B",
    "decorCircle2": "#B37C4C"
  },
  "fonts": {
    "headingFamily": "'Playfair Display Bold', 'Playfair Display', Georgia, serif",
    "bodyFamily": "'Montserrat', 'Helvetica Neue', Arial, sans-serif",
    "titleSize": "56px",
    "h1Size": "42px",
    "h2Size": "28px",
    "bulletLabelSize": "24px",
    "bulletBodySize": "14px",
    "noteSize": "11px",
    "captionSize": "10px",
    "footerSize": "7.3px",
    "titleWeight": "700",
    "h1Weight": "700",
    "h2Weight": "700",
    "bulletLabelWeight": "700",
    "bulletBodyWeight": "400",
    "footerWeight": "700",
    "footerStyle": "italic",
    "lineHeightTitle": "1.1",
    "lineHeightBody": "1.6"
  },
  "layout": {
    "slideWidthPt": 1440,
    "slideHeightPt": 810,
    "slideAspectRatio": "16:9",
    "presentationPageWidth": "596pt",
    "presentationPageHeight": "842pt",
    "presentationSlideTop": "0pt",
    "presentationSlideHeight": "512pt",
    "presentationNotesTop": "512pt",
    "presentationNotesHeight": "294pt",
    "presentationMarginX": "36pt",
    "presentationMarginBottom": "36pt",
    "assessmentPageWidth": "612pt",
    "assessmentPageHeight": "792pt",
    "assessmentMarginLeft": "20pt",
    "assessmentMarginRight": "18pt",
    "assessmentMarginTop": "13pt",
    "assessmentMarginBottom": "21pt",
    "assessmentColumnCount": 2,
    "assessmentColumnGap": "20pt",
    "summaryPageWidth": "612pt",
    "summaryPageHeight": "792pt",
    "summaryMarginLeft": "20pt",
    "summaryMarginRight": "29pt",
    "summaryMarginTop": "20pt",
    "summaryMarginBottom": "43pt",
    "slideMaxWidthPx": 1040,
    "pagePadding": "28px",
    "sectionPaddingX": "28px",
    "sectionPaddingY": "20px",
    "sectionGap": "16px",
    "bulletGap": "8px",
    "borderRadius": "8px",
    "borderColor": "#D1CFC6",
    "borderWidth": "1px"
  },
  "shapes": {
    "cornerCircle1Color": "#8A9A5B",
    "cornerCircle1Size": "88px",
    "cornerCircle1OpacityPct": 100,
    "cornerCircle2Color": "#B37C4C",
    "cornerCircle2Size": "60px",
    "cornerCircle2Offset": "24px",
    "cornerCircleOpacity": "0.85"
  },
  "imagery": {
    "imageMaxHeight": "200px",
    "imageBorderRadius": "6px",
    "imageMarginBottom": "12px"
  },
  "assessment": {
    "headerFont": "Montserrat",
    "headerSize": "10pt",
    "headerWeight": "700",
    "questionFont": "Montserrat",
    "questionSize": "9.5pt",
    "questionWeight": "700",
    "choiceFont": "Montserrat",
    "choiceSize": "9.5pt",
    "choiceWeight": "400",
    "footerFont": "Montserrat",
    "footerSize": "7.3pt",
    "footerWeight": "700",
    "footerStyle": "italic",
    "footerColor": "#5E6A71",
    "textAlign": "justify",
    "background": "#E6E5DE"
  },
  "presentation": {
    "titleFont": "Playfair Display Bold",
    "titleSize": "56pt",
    "titleColor": "#4A6631",
    "h2Font": "Playfair Display Bold",
    "h2Size": "42pt",
    "h2Color": "#4A6631",
    "subtitleFont": "Montserrat Bold",
    "subtitleSize": "28pt",
    "subtitleColor": "#B37C4C",
    "bulletLabelFont": "Montserrat Bold",
    "bulletLabelSize": "24pt",
    "bulletLabelColor": "#C06C4D",
    "bulletBodyFont": "Montserrat",
    "bulletBodySize": "24pt",
    "bulletBodyColor": "#000000",
    "notesFont": "CanvaSans, Montserrat",
    "notesSize": "10pt",
    "notesColor": "#000000",
    "slideBackground": "#E6E5DE",
    "notesBackground": "#E6E5DE"
  },
  "summary": {
    "font": "Montserrat",
    "boldSize": "12pt",
    "regularSize": "12pt",
    "color": "#5E6A71",
    "background": "#E6E5DE"
  }
}
